{
  "ComponentIndexes": {},
  "ControlUniqueGuids": {},
  "ControlUniqueIds": {
    "App": 1,
    "BodyContainer": 30,
    "Button9": 21,
    "Container10": 16,
    "Container10_1": 59,
    "Container3": 34,
    "Container4": 33,
    "Container6": 40,
    "Container6_1": 37,
    "DashboardContainer": 31,
    "DashboardLabelContainer": 28,
    "EssentialLabel5_5": 43,
    "Gallery1": 60,
    "Gallery4": 17,
    "galleryTemplate1": 61,
    "galleryTemplate4": 18,
    "HeaderContainer": 27,
    "HeaderContainer_1": 54,
    "HeaderContainer1": 8,
    "HomeScreen": 23,
    "Host": 3,
    "Icon2": 35,
    "Icon5": 41,
    "Icon5_1": 38,
    "Icon6": 9,
    "Image1": 25,
    "Image1_1": 6,
    "Image1_2": 52,
    "ImageContainer": 24,
    "ImageContainer_1": 5,
    "ImageContainer_2": 51,
    "Label1": 26,
    "Label1_1": 7,
    "Label1_2": 53,
    "Label10": 29,
    "Label12": 13,
    "Label12_1": 58,
    "Label13": 14,
    "Label13_1": 15,
    "Label17": 11,
    "Label17_1": 56,
    "Label18": 22,
    "Label18_1": 20,
    "Label2_1": 62,
    "Label3": 36,
    "Label5_1": 45,
    "Label5_2": 44,
    "Label5_3": 47,
    "Label5_4": 46,
    "Label6": 42,
    "Label6_1": 39,
    "Label7": 32,
    "ListBodyContainer": 10,
    "ListHeaderContainer": 12,
    "ListHeaderContainer_1": 57,
    "NiomineeButton": 48,
    "NominateButton": 64,
    "NomineeListScreen": 4,
    "Rectangle1": 19,
    "RedeemButton": 49,
    "RedemptionBodyContainer": 55,
    "RedemptionScreen": 50,
    "Screen2": 63
  },
  "FunctionParamsInvariantScripts": {},
  "FunctionParamsInvariantScriptsOnInstances": {},
  "HeaderLastSavedDateTimeUTC": "04/26/2024 06:57:24",
  "IsLegacyComponentAllowGlobalScopeCase": false,
  "LocalConnectionIDReferences": {
    "b7b7295d-881e-487e-9b09-2c6455248e20": "\"/providers/microsoft.powerapps/apis/shared_sharepointonline/connections/ee873bcf1842400fa64d2a177fca4e5d\""
  },
  "LocalDatabaseReferencesAsEmpty": true,
  "LocalResourceFileNames": {},
  "LocalResourceRootPaths": {},
  "OrderComponentMetadata": {},
  "OrderComponentTemplate": {},
  "OrderDataSource": {
    "CustomGallerySample": 0,
    "DropDownSample": 1,
    "Managers&Approvers": 2,
    "NomineeList": 3,
    "PrizeList": 4
  },
  "OrderGroupControls": {},
  "OrderPcfTemplate": {},
  "OrderTemplate": {},
  "OrderXMLTemplate": {
    "button": 6,
    "gallery": 4,
    "groupContainer": 0,
    "icon": 1,
    "image": 2,
    "label": 3,
    "rectangle": 5
  },
  "OverridablePropertiesEntry": {
    "App": {},
    "BodyContainer": {},
    "Button9": {},
    "Container10": {},
    "Container10_1": {},
    "Container3": {},
    "Container4": {},
    "Container6": {},
    "Container6_1": {},
    "DashboardContainer": {},
    "DashboardLabelContainer": {},
    "EssentialLabel5_5": {},
    "Gallery1": {},
    "Gallery4": {},
    "galleryTemplate1": {},
    "galleryTemplate4": {},
    "HeaderContainer": {},
    "HeaderContainer_1": {},
    "HeaderContainer1": {},
    "HomeScreen": {},
    "Host": {},
    "Icon2": {},
    "Icon5": {},
    "Icon5_1": {},
    "Icon6": {},
    "Image1": {},
    "Image1_1": {},
    "Image1_2": {},
    "ImageContainer": {},
    "ImageContainer_1": {},
    "ImageContainer_2": {},
    "Label1": {},
    "Label1_1": {},
    "Label1_2": {},
    "Label10": {},
    "Label12": {},
    "Label12_1": {},
    "Label13": {},
    "Label13_1": {},
    "Label17": {},
    "Label17_1": {},
    "Label18": {},
    "Label18_1": {},
    "Label2_1": {},
    "Label3": {},
    "Label5_1": {},
    "Label5_2": {},
    "Label5_3": {},
    "Label5_4": {},
    "Label6": {},
    "Label6_1": {},
    "Label7": {},
    "ListBodyContainer": {},
    "ListHeaderContainer": {},
    "ListHeaderContainer_1": {},
    "NiomineeButton": {},
    "NominateButton": {},
    "NomineeListScreen": {},
    "Rectangle1": {},
    "RedeemButton": {},
    "RedemptionBodyContainer": {},
    "RedemptionScreen": {},
    "Screen2": {}
  },
  "PCFDynamicSchemaForIRRetrievalEntry": {},
  "PCFTemplateEntry": {},
  "PublishOrderIndices": {
    "App": 0,
    "BodyContainer": 6,
    "Button9": 42,
    "Container10": 37,
    "Container10_1": 52,
    "Container3": 11,
    "Container4": 9,
    "Container6": 17,
    "Container6_1": 14,
    "DashboardContainer": 7,
    "DashboardLabelContainer": 4,
    "EssentialLabel5_5": 10,
    "Gallery1": 53,
    "Gallery4": 38,
    "galleryTemplate1": 54,
    "galleryTemplate4": 39,
    "HeaderContainer": 3,
    "HeaderContainer_1": 44,
    "HeaderContainer1": 26,
    "HomeScreen": 3,
    "Host": 0,
    "Icon2": 12,
    "Icon5": 18,
    "Icon5_1": 15,
    "Icon6": 27,
    "Image1": 1,
    "Image1_1": 29,
    "Image1_2": 46,
    "ImageContainer": 0,
    "ImageContainer_1": 28,
    "ImageContainer_2": 45,
    "Label1": 2,
    "Label1_1": 30,
    "Label1_2": 47,
    "Label10": 5,
    "Label12": 34,
    "Label12_1": 51,
    "Label13": 35,
    "Label13_1": 36,
    "Label17": 32,
    "Label17_1": 49,
    "Label18": 43,
    "Label18_1": 41,
    "Label2_1": 55,
    "Label3": 13,
    "Label5_1": 21,
    "Label5_2": 20,
    "Label5_3": 23,
    "Label5_4": 22,
    "Label6": 19,
    "Label6_1": 16,
    "Label7": 8,
    "ListBodyContainer": 31,
    "ListHeaderContainer": 33,
    "ListHeaderContainer_1": 50,
    "NiomineeButton": 24,
    "NominateButton": 25,
    "NomineeListScreen": 30,
    "Rectangle1": 40,
    "RedeemButton": 25,
    "RedemptionBodyContainer": 48,
    "RedemptionScreen": 49,
    "Screen2": 62
  },
  "ResourcesJsonIndices": {
    "Image-SampleImage": 0
  },
  "RuleScreenIdWithoutScreen": {},
  "TemplateVersions": {},
  "VolatileProperties": {
    "AnalysisLoadTime": 0.4181396,
    "ControlCount": {
      "button": 4,
      "gallery": 2,
      "galleryTemplate": 2,
      "groupContainer": 19,
      "icon": 4,
      "image": 3,
      "label": 22,
      "rectangle": 1,
      "screen": 4
    },
    "DeserializationLoadTime": 1.4699784
  },
  "WasLocalDatabaseReferencesEmpty": true
}