{
  "ComponentIndexes": {},
  "ControlUniqueGuids": {},
  "ControlUniqueIds": {
    "App": 1,
    "ApprovalContainer": 60,
    "ApprovalScreen": 26,
    "ApproveButton": 25,
    "ApproveContainer": 18,
    "BodyContainer": 11,
    "BodyContainer_1": 27,
    "Button1": 77,
    "Button19": 128,
    "Button9": 107,
    "ComboBox1": 39,
    "Container1": 35,
    "Container1_1": 41,
    "Container1_2": 48,
    "Container1_3": 54,
    "Container1_4": 63,
    "Container1_5": 69,
    "Container10": 102,
    "Container19": 120,
    "Container4": 14,
    "Container5_2": 53,
    "Container7": 38,
    "Container7_1": 51,
    "Container7_2": 57,
    "Container7_3": 66,
    "Container7_4": 72,
    "DashboardContainer": 12,
    "DashboardContainer_1": 29,
    "DashboardLabelContainer": 9,
    "DashboardLabelContainer_1": 87,
    "DatePicker1": 73,
    "DatePicker2": 58,
    "EssentialLabel5_5": 17,
    "FormBodyContainer": 31,
    "Gallery4": 103,
    "Gallery6": 122,
    "galleryTemplate4": 104,
    "galleryTemplate6": 123,
    "HeaderContainer": 5,
    "HeaderContainer_1": 110,
    "HeaderContainer_2": 81,
    "HeaderContainer1": 90,
    "HomeIcon": 82,
    "HomeScreen": 4,
    "Host": 3,
    "Icon1": 111,
    "Icon6": 91,
    "Image1": 7,
    "Image1_1": 94,
    "Image1_2": 114,
    "Image1_3": 85,
    "ImageContainer": 6,
    "ImageContainer_1": 93,
    "ImageContainer_2": 113,
    "ImageContainer_3": 84,
    "Label1": 8,
    "Label1_1": 95,
    "Label1_2": 115,
    "Label1_3": 86,
    "Label10": 10,
    "Label10_1": 88,
    "Label11": 83,
    "Label11_1": 92,
    "Label11_2": 112,
    "Label12": 99,
    "Label13": 100,
    "Label13_1": 101,
    "Label14": 121,
    "Label17": 97,
    "Label18": 108,
    "Label18_1": 106,
    "Label2": 37,
    "Label2_2": 43,
    "Label2_3": 50,
    "Label2_4": 56,
    "Label2_5": 65,
    "Label2_6": 71,
    "Label4": 36,
    "Label4_1": 42,
    "Label4_2": 49,
    "Label4_3": 55,
    "Label4_4": 64,
    "Label4_5": 70,
    "Label5": 78,
    "Label5_1": 20,
    "Label5_2": 19,
    "Label5_3": 21,
    "Label5_4": 22,
    "Label5_5": 80,
    "Label7": 13,
    "Label7_1": 30,
    "Label7_2": 28,
    "Label7_3": 45,
    "Label7_4": 74,
    "Label7_5": 59,
    "Label7_6": 75,
    "Label8": 118,
    "Label9": 119,
    "ListBodyContainer": 96,
    "ListHeaderContainer": 98,
    "ListHeaderContainer_1": 117,
    "NameContainer": 33,
    "NameContainer_1": 61,
    "NextArrow9": 126,
    "NominationContainer": 32,
    "NominatorContainer": 40,
    "NominatorContainer_1": 68,
    "NomineeButton": 23,
    "NomineeContainer": 15,
    "NomineeListScreen": 89,
    "NomineeNameContainer": 34,
    "NomineeNameContainer_1": 47,
    "NomineeNameContainer_2": 62,
    "OthersContainer": 46,
    "Rectangle1": 105,
    "Rectangle10": 124,
    "RedeemButton": 24,
    "RedemptionBodyContainer": 116,
    "RedemptionContainer": 16,
    "RedemptionScreen": 109,
    "Separator9": 129,
    "SubmitButton": 79,
    "SubmitContainer": 76,
    "Subtitle9": 127,
    "TextInput1": 44,
    "TextInput1_2": 67,
    "TextInput2": 52,
    "Title10": 125
  },
  "FunctionParamsInvariantScripts": {},
  "FunctionParamsInvariantScriptsOnInstances": {},
  "HeaderLastSavedDateTimeUTC": "04/29/2024 08:56:28",
  "IsLegacyComponentAllowGlobalScopeCase": false,
  "LocalConnectionIDReferences": {
    "b7b7295d-881e-487e-9b09-2c6455248e20": "\"/providers/microsoft.powerapps/apis/shared_sharepointonline/connections/ee873bcf1842400fa64d2a177fca4e5d\""
  },
  "LocalDatabaseReferencesAsEmpty": true,
  "LocalResourceFileNames": {},
  "LocalResourceRootPaths": {},
  "OrderComponentMetadata": {},
  "OrderComponentTemplate": {},
  "OrderDataSource": {
    "ComboBoxSample": 0,
    "CustomGallerySample": 1,
    "DropDownSample": 2,
    "Managers&Approvers": 3,
    "NomineeList": 4,
    "PrizeList": 5
  },
  "OrderGroupControls": {},
  "OrderPcfTemplate": {},
  "OrderTemplate": {},
  "OrderXMLTemplate": {
    "button": 3,
    "combobox": 4,
    "datepicker": 6,
    "gallery": 8,
    "groupContainer": 0,
    "icon": 7,
    "image": 1,
    "label": 2,
    "rectangle": 9,
    "text": 5
  },
  "OverridablePropertiesEntry": {
    "App": {},
    "ApprovalContainer": {},
    "ApprovalScreen": {},
    "ApproveButton": {},
    "ApproveContainer": {},
    "BodyContainer": {},
    "BodyContainer_1": {},
    "Button1": {},
    "Button19": {},
    "Button9": {},
    "ComboBox1": {},
    "Container1": {},
    "Container1_1": {},
    "Container1_2": {},
    "Container1_3": {},
    "Container1_4": {},
    "Container1_5": {},
    "Container10": {},
    "Container19": {},
    "Container4": {},
    "Container5_2": {},
    "Container7": {},
    "Container7_1": {},
    "Container7_2": {},
    "Container7_3": {},
    "Container7_4": {},
    "DashboardContainer": {},
    "DashboardContainer_1": {},
    "DashboardLabelContainer": {},
    "DashboardLabelContainer_1": {},
    "DatePicker1": {},
    "DatePicker2": {},
    "EssentialLabel5_5": {},
    "FormBodyContainer": {},
    "Gallery4": {},
    "Gallery6": {},
    "galleryTemplate4": {},
    "galleryTemplate6": {},
    "HeaderContainer": {},
    "HeaderContainer_1": {},
    "HeaderContainer_2": {},
    "HeaderContainer1": {},
    "HomeIcon": {},
    "HomeScreen": {},
    "Host": {},
    "Icon1": {},
    "Icon6": {},
    "Image1": {},
    "Image1_1": {},
    "Image1_2": {},
    "Image1_3": {},
    "ImageContainer": {},
    "ImageContainer_1": {},
    "ImageContainer_2": {},
    "ImageContainer_3": {},
    "Label1": {},
    "Label1_1": {},
    "Label1_2": {},
    "Label1_3": {},
    "Label10": {},
    "Label10_1": {},
    "Label11": {},
    "Label11_1": {},
    "Label11_2": {},
    "Label12": {},
    "Label13": {},
    "Label13_1": {},
    "Label14": {},
    "Label17": {},
    "Label18": {},
    "Label18_1": {},
    "Label2": {},
    "Label2_2": {},
    "Label2_3": {},
    "Label2_4": {},
    "Label2_5": {},
    "Label2_6": {},
    "Label4": {},
    "Label4_1": {},
    "Label4_2": {},
    "Label4_3": {},
    "Label4_4": {},
    "Label4_5": {},
    "Label5": {},
    "Label5_1": {},
    "Label5_2": {},
    "Label5_3": {},
    "Label5_4": {},
    "Label5_5": {},
    "Label7": {},
    "Label7_1": {},
    "Label7_2": {},
    "Label7_3": {},
    "Label7_4": {},
    "Label7_5": {},
    "Label7_6": {},
    "Label8": {},
    "Label9": {},
    "ListBodyContainer": {},
    "ListHeaderContainer": {},
    "ListHeaderContainer_1": {},
    "NameContainer": {},
    "NameContainer_1": {},
    "NextArrow9": {},
    "NominationContainer": {},
    "NominatorContainer": {},
    "NominatorContainer_1": {},
    "NomineeButton": {},
    "NomineeContainer": {},
    "NomineeListScreen": {},
    "NomineeNameContainer": {},
    "NomineeNameContainer_1": {},
    "NomineeNameContainer_2": {},
    "OthersContainer": {},
    "Rectangle1": {},
    "Rectangle10": {},
    "RedeemButton": {},
    "RedemptionBodyContainer": {},
    "RedemptionContainer": {},
    "RedemptionScreen": {},
    "Separator9": {},
    "SubmitButton": {},
    "SubmitContainer": {},
    "Subtitle9": {},
    "TextInput1": {},
    "TextInput1_2": {},
    "TextInput2": {},
    "Title10": {}
  },
  "PCFDynamicSchemaForIRRetrievalEntry": {},
  "PCFTemplateEntry": {},
  "PublishOrderIndices": {
    "App": 0,
    "ApprovalContainer": 14,
    "ApprovalScreen": 3,
    "ApproveButton": 73,
    "ApproveContainer": 83,
    "BodyContainer": 70,
    "BodyContainer_1": 4,
    "Button1": 57,
    "Button19": 127,
    "Button9": 106,
    "ComboBox1": 26,
    "Container1": 22,
    "Container1_1": 27,
    "Container1_2": 33,
    "Container1_3": 38,
    "Container1_4": 47,
    "Container1_5": 52,
    "Container10": 98,
    "Container19": 117,
    "Container4": 79,
    "Container5_2": 32,
    "Container7": 23,
    "Container7_1": 34,
    "Container7_2": 39,
    "Container7_3": 48,
    "Container7_4": 53,
    "DashboardContainer": 77,
    "DashboardContainer_1": 9,
    "DashboardLabelContainer": 69,
    "DashboardLabelContainer_1": 7,
    "DatePicker1": 56,
    "DatePicker2": 42,
    "EssentialLabel5_5": 82,
    "FormBodyContainer": 11,
    "Gallery4": 102,
    "Gallery6": 121,
    "galleryTemplate4": 103,
    "galleryTemplate6": 122,
    "HeaderContainer": 67,
    "HeaderContainer_1": 109,
    "HeaderContainer_2": 5,
    "HeaderContainer1": 89,
    "HomeIcon": 61,
    "HomeScreen": 66,
    "Host": 0,
    "Icon1": 112,
    "Icon6": 92,
    "Image1": 74,
    "Image1_1": 94,
    "Image1_2": 114,
    "Image1_3": 63,
    "ImageContainer": 68,
    "ImageContainer_1": 90,
    "ImageContainer_2": 110,
    "ImageContainer_3": 6,
    "Label1": 75,
    "Label1_1": 95,
    "Label1_2": 115,
    "Label1_3": 64,
    "Label10": 76,
    "Label10_1": 65,
    "Label11": 62,
    "Label11_1": 93,
    "Label11_2": 113,
    "Label12": 99,
    "Label13": 100,
    "Label13_1": 101,
    "Label14": 120,
    "Label17": 96,
    "Label18": 107,
    "Label18_1": 105,
    "Label2": 25,
    "Label2_2": 30,
    "Label2_3": 36,
    "Label2_4": 41,
    "Label2_5": 50,
    "Label2_6": 55,
    "Label4": 24,
    "Label4_1": 29,
    "Label4_2": 35,
    "Label4_3": 40,
    "Label4_4": 49,
    "Label4_5": 54,
    "Label5": 58,
    "Label5_1": 85,
    "Label5_2": 84,
    "Label5_3": 86,
    "Label5_4": 87,
    "Label5_5": 60,
    "Label7": 78,
    "Label7_1": 10,
    "Label7_2": 8,
    "Label7_3": 18,
    "Label7_4": 44,
    "Label7_5": 13,
    "Label7_6": 15,
    "Label8": 118,
    "Label9": 119,
    "ListBodyContainer": 91,
    "ListHeaderContainer": 97,
    "ListHeaderContainer_1": 116,
    "NameContainer": 17,
    "NameContainer_1": 43,
    "NextArrow9": 125,
    "NominationContainer": 12,
    "NominatorContainer": 21,
    "NominatorContainer_1": 46,
    "NomineeButton": 71,
    "NomineeContainer": 80,
    "NomineeListScreen": 88,
    "NomineeNameContainer": 20,
    "NomineeNameContainer_1": 31,
    "NomineeNameContainer_2": 45,
    "OthersContainer": 19,
    "Rectangle1": 104,
    "Rectangle10": 123,
    "RedeemButton": 72,
    "RedemptionBodyContainer": 111,
    "RedemptionContainer": 81,
    "RedemptionScreen": 108,
    "Separator9": 128,
    "SubmitButton": 59,
    "SubmitContainer": 16,
    "Subtitle9": 126,
    "TextInput1": 28,
    "TextInput1_2": 51,
    "TextInput2": 37,
    "Title10": 124
  },
  "ResourcesJsonIndices": {
    "Image-SampleImage": 0
  },
  "RuleScreenIdWithoutScreen": {},
  "TemplateVersions": {},
  "VolatileProperties": {
    "AnalysisLoadTime": 1.4863867,
    "ControlCount": {
      "button": 7,
      "combobox": 1,
      "datepicker": 2,
      "gallery": 2,
      "galleryTemplate": 2,
      "groupContainer": 48,
      "icon": 4,
      "image": 4,
      "label": 46,
      "rectangle": 3,
      "screen": 4,
      "text": 3
    },
    "DeserializationLoadTime": 2.0062124
  },
  "WasLocalDatabaseReferencesEmpty": true
}